pg2ch/__init__.py
pg2ch/main.py
pg2ch/converters/__init__.py
pg2ch/converters/base_converter.py
pg2ch/converters/clickhouse_converter.py
pg2ch/models/__init__.py
pg2ch/models/column.py
pg2ch/models/constraints.py
pg2ch/models/table.py
pg2ch/parsers/__init__.py
pg2ch/parsers/base_parser.py
pg2ch/parsers/postgres_parser.py
pg2ch/utils/__init__.py
pg2ch/utils/exceptions.py
pg2ch/utils/helpers.py
pg2ch/utils/logging_config.py
pg2ch/validators/__init__.py
pg2ch/validators/validate_ch_ddl.py
pg2ch-0.1.1.dist-info/licenses/LICENSE
pg2ch-0.1.1.dist-info/METADATA
pg2ch-0.1.1.dist-info/WHEEL
pg2ch-0.1.1.dist-info/entry_points.txt
pg2ch-0.1.1.dist-info/top_level.txt
pg2ch-0.1.1.dist-info/RECORD
